[
    {
        "name": "持込先1",
        "account_id": 1
    },
    {
        "name": "持込先2",
        "account_id": 1
    },
    {
        "name": "持込先3",
        "account_id": 1
    },
    {
        "name": "持込先4",
        "account_id": 1
    },
    {
        "name": "持込先5",
        "account_id": 1
    },
    {
        "name": "持込先6",
        "account_id": 1
    },
    {
        "name": "持込先7",
        "account_id": 1
    },
    {
        "name": "持込先8",
        "account_id": 1
    },
    {
        "name": "持込先9",
        "account_id": 1
    },
    {
        "name": "持込先10",
        "account_id": 1
    },
    {
        "name": "持込先11",
        "account_id": 2
    },
    {
        "name": "持込先12",
        "account_id": 2
    },
    {
        "name": "持込先13",
        "account_id": 2
    },
    {
        "name": "持込先14",
        "account_id": 2
    },
    {
        "name": "持込先15",
        "account_id": 2
    },
    {
        "name": "持込先16",
        "account_id": 2
    },
    {
        "name": "持込先17",
        "account_id": 2
    },
    {
        "name": "持込先18",
        "account_id": 2
    },
    {
        "name": "持込先19",
        "account_id": 2
    },
    {
        "name": "持込先20",
        "account_id": 2
    },
    {
        "name": "持込先21",
        "account_id": 2
    },
    {
        "name": "持込先22",
        "account_id": 2
    },
    {
        "name": "持込先23",
        "account_id": 2
    },
    {
        "name": "持込先24",
        "account_id": 2
    },
    {
        "name": "持込先25",
        "account_id": 2
    }
]